acglib/__init__.py
acglib/aws/__init__.py
acglib/aws/iamhelper.py
acglib/aws/regionhelper.py
acglib-0.2.dist-info/LICENSE
acglib-0.2.dist-info/METADATA
acglib-0.2.dist-info/WHEEL
acglib-0.2.dist-info/top_level.txt
acglib-0.2.dist-info/RECORD
